[{"flows": [{"origin_node": 23, "destination": 22, "origin_node_antenna": 12, "path": "[23, 12, 9, 7, 4, 1, 0, 3, 22]", "bandwidth": 18000000, "traffic_string": "0,18000000,1500,10,2,6000,12000,18000"}], "delta": 0.35, "type": "eMBB", "number": 0}, {"flows": [{"origin_node": 35, "destination": 22, "origin_node_antenna": 5, "path": "[35, 5, 8, 6, 14, 0, 1, 3, 22]", "bandwidth": 18000000, "traffic_string": "0,18000000,1500,10,2,6000,12000,18000"}, {"origin_node": 70, "destination": 22, "origin_node_antenna": 12, "path": "[70, 12, 9, 13, 14, 16, 2, 3, 22]", "bandwidth": 18000000, "traffic_string": "0,18000000,1500,10,2,6000,12000,18000"}], "delta": 0.575, "type": "eMBB", "number": 1}, {"flows": [{"origin_node": 43, "destination": 22, "origin_node_antenna": 5, "path": "[43, 5, 6, 8, 9, 12, 13, 14, 16, 2, 3, 22]", "bandwidth": 18000000, "traffic_string": "0,18000000,1500,10,2,6000,12000,18000"}], "delta": 0.155, "type": "eMBB", "number": 2}, {"flows": [{"origin_node": 36, "destination": 22, "origin_node_antenna": 5, "path": "[36, 5, 6, 8, 9, 7, 4, 1, 0, 3, 22]", "bandwidth": 18000000, "traffic_string": "0,18000000,1500,10,2,6000,12000,18000"}, {"origin_node": 93, "destination": 22, "origin_node_antenna": 12, "path": "[93, 12, 13, 9, 14, 16, 2, 3, 22]", "bandwidth": 18000000, "traffic_string": "0,18000000,1500,10,2,6000,12000,18000"}], "delta": 0.704, "type": "eMBB", "number": 3}, {"flows": [{"origin_node": 24, "destination": 22, "origin_node_antenna": 5, "path": "[24, 5, 8, 6, 14, 0, 1, 3, 22]", "bandwidth": 18000000, "traffic_string": "0,18000000,1500,10,2,6000,12000,18000"}], "delta": 0.237, "type": "eMBB", "number": 4}, {"flows": [{"origin_node": 25, "destination": 22, "origin_node_antenna": 9, "path": "[25, 9, 7, 4, 1, 0, 3, 22]", "bandwidth": 18000000, "traffic_string": "0,18000000,1500,10,2,6000,12000,18000"}], "delta": 0.141, "type": "eMBB", "number": 5}, {"flows": [{"origin_node": 44, "destination": 21, "origin_node_antenna": 5, "path": "[44, 5, 8, 6, 14, 0, 1, 3, 2, 16, 17, 18, 21]", "bandwidth": 200000, "traffic_string": "0,200000,625,10,2,160,320,480"}, {"origin_node": 49, "destination": 21, "origin_node_antenna": 5, "path": "[49, 5, 8, 6, 14, 0, 1, 3, 2, 16, 17, 18, 21]", "bandwidth": 200000, "traffic_string": "0,200000,625,10,2,160,320,480"}, {"origin_node": 50, "destination": 21, "origin_node_antenna": 5, "path": "[50, 5, 8, 6, 14, 0, 1, 3, 2, 16, 17, 18, 21]", "bandwidth": 200000, "traffic_string": "0,200000,625,10,2,160,320,480"}, {"origin_node": 55, "destination": 21, "origin_node_antenna": 5, "path": "[55, 5, 8, 6, 14, 0, 1, 3, 2, 16, 17, 18, 21]", "bandwidth": 200000, "traffic_string": "0,200000,625,10,2,160,320,480"}, {"origin_node": 56, "destination": 21, "origin_node_antenna": 5, "path": "[56, 5, 8, 6, 14, 0, 1, 3, 2, 16, 17, 18, 21]", "bandwidth": 200000, "traffic_string": "0,200000,625,10,2,160,320,480"}, {"origin_node": 57, "destination": 21, "origin_node_antenna": 5, "path": "[57, 5, 8, 6, 14, 0, 1, 3, 2, 16, 17, 18, 21]", "bandwidth": 200000, "traffic_string": "0,200000,625,10,2,160,320,480"}, {"origin_node": 58, "destination": 21, "origin_node_antenna": 5, "path": "[58, 5, 8, 6, 14, 0, 1, 3, 2, 16, 17, 18, 21]", "bandwidth": 200000, "traffic_string": "0,200000,625,10,2,160,320,480"}, {"origin_node": 60, "destination": 21, "origin_node_antenna": 5, "path": "[60, 5, 8, 6, 14, 0, 1, 3, 2, 16, 17, 18, 21]", "bandwidth": 200000, "traffic_string": "0,200000,625,10,2,160,320,480"}, {"origin_node": 62, "destination": 21, "origin_node_antenna": 5, "path": "[62, 5, 8, 6, 14, 0, 1, 3, 2, 16, 17, 18, 21]", "bandwidth": 200000, "traffic_string": "0,200000,625,10,2,160,320,480"}, {"origin_node": 64, "destination": 21, "origin_node_antenna": 5, "path": "[64, 5, 8, 6, 14, 0, 1, 3, 2, 16, 17, 18, 21]", "bandwidth": 200000, "traffic_string": "0,200000,625,10,2,160,320,480"}, {"origin_node": 67, "destination": 21, "origin_node_antenna": 5, "path": "[67, 5, 6, 8, 9, 7, 4, 1, 0, 3, 2, 16, 17, 18, 21]", "bandwidth": 200000, "traffic_string": "0,200000,625,10,2,160,320,480"}, {"origin_node": 81, "destination": 21, "origin_node_antenna": 12, "path": "[81, 12, 9, 7, 4, 1, 0, 3, 2, 16, 17, 18, 21]", "bandwidth": 200000, "traffic_string": "0,200000,625,10,2,160,320,480"}, {"origin_node": 85, "destination": 21, "origin_node_antenna": 12, "path": "[85, 12, 9, 13, 14, 16, 2, 11, 10, 19, 18, 21]", "bandwidth": 200000, "traffic_string": "0,200000,625,10,2,160,320,480"}, {"origin_node": 87, "destination": 21, "origin_node_antenna": 12, "path": "[87, 12, 9, 13, 14, 16, 2, 11, 10, 19, 18, 21]", "bandwidth": 200000, "traffic_string": "0,200000,625,10,2,160,320,480"}, {"origin_node": 94, "destination": 21, "origin_node_antenna": 12, "path": "[94, 12, 9, 13, 14, 16, 2, 11, 10, 19, 18, 21]", "bandwidth": 200000, "traffic_string": "0,200000,625,10,2,160,320,480"}, {"origin_node": 95, "destination": 21, "origin_node_antenna": 12, "path": "[95, 12, 9, 13, 14, 16, 2, 11, 10, 19, 18, 21]", "bandwidth": 200000, "traffic_string": "0,200000,625,10,2,160,320,480"}, {"origin_node": 96, "destination": 21, "origin_node_antenna": 12, "path": "[96, 12, 9, 13, 14, 16, 2, 11, 10, 19, 18, 21]", "bandwidth": 200000, "traffic_string": "0,200000,625,10,2,160,320,480"}, {"origin_node": 97, "destination": 21, "origin_node_antenna": 12, "path": "[97, 12, 9, 13, 14, 16, 2, 11, 10, 19, 18, 21]", "bandwidth": 200000, "traffic_string": "0,200000,625,10,2,160,320,480"}, {"origin_node": 98, "destination": 21, "origin_node_antenna": 12, "path": "[98, 12, 9, 13, 14, 16, 2, 11, 10, 19, 18, 21]", "bandwidth": 200000, "traffic_string": "0,200000,625,10,2,160,320,480"}, {"origin_node": 99, "destination": 21, "origin_node_antenna": 12, "path": "[99, 12, 9, 13, 14, 16, 2, 11, 10, 19, 18, 21]", "bandwidth": 200000, "traffic_string": "0,200000,625,10,2,160,320,480"}, {"origin_node": 100, "destination": 21, "origin_node_antenna": 12, "path": "[100, 12, 9, 13, 14, 16, 2, 11, 10, 19, 18, 21]", "bandwidth": 200000, "traffic_string": "0,200000,625,10,2,160,320,480"}, {"origin_node": 102, "destination": 21, "origin_node_antenna": 12, "path": "[102, 12, 9, 13, 14, 16, 2, 11, 10, 19, 18, 21]", "bandwidth": 200000, "traffic_string": "0,200000,625,10,2,160,320,480"}, {"origin_node": 103, "destination": 21, "origin_node_antenna": 12, "path": "[103, 12, 9, 13, 14, 16, 2, 11, 10, 19, 18, 21]", "bandwidth": 200000, "traffic_string": "0,200000,625,10,2,160,320,480"}, {"origin_node": 105, "destination": 21, "origin_node_antenna": 12, "path": "[105, 12, 13, 9, 14, 16, 2, 11, 10, 19, 18, 21]", "bandwidth": 200000, "traffic_string": "0,200000,625,10,2,160,320,480"}, {"origin_node": 110, "destination": 21, "origin_node_antenna": 12, "path": "[110, 12, 13, 9, 14, 16, 2, 11, 10, 19, 18, 21]", "bandwidth": 200000, "traffic_string": "0,200000,625,10,2,160,320,480"}, {"origin_node": 111, "destination": 21, "origin_node_antenna": 12, "path": "[111, 12, 13, 9, 14, 16, 2, 11, 10, 19, 18, 21]", "bandwidth": 200000, "traffic_string": "0,200000,625,10,2,160,320,480"}, {"origin_node": 112, "destination": 21, "origin_node_antenna": 12, "path": "[112, 12, 13, 9, 14, 16, 2, 11, 10, 19, 18, 21]", "bandwidth": 200000, "traffic_string": "0,200000,625,10,2,160,320,480"}, {"origin_node": 123, "destination": 21, "origin_node_antenna": 9, "path": "[123, 9, 13, 14, 16, 2, 11, 10, 19, 18, 21]", "bandwidth": 200000, "traffic_string": "0,200000,625,10,2,160,320,480"}, {"origin_node": 125, "destination": 21, "origin_node_antenna": 9, "path": "[125, 9, 13, 14, 16, 2, 11, 10, 19, 18, 21]", "bandwidth": 200000, "traffic_string": "0,200000,625,10,2,160,320,480"}, {"origin_node": 126, "destination": 21, "origin_node_antenna": 9, "path": "[126, 9, 13, 14, 16, 2, 11, 10, 19, 18, 21]", "bandwidth": 200000, "traffic_string": "0,200000,625,10,2,160,320,480"}, {"origin_node": 127, "destination": 21, "origin_node_antenna": 9, "path": "[127, 9, 13, 14, 16, 2, 11, 10, 19, 18, 21]", "bandwidth": 200000, "traffic_string": "0,200000,625,10,2,160,320,480"}, {"origin_node": 128, "destination": 21, "origin_node_antenna": 9, "path": "[128, 9, 13, 14, 16, 2, 11, 10, 19, 18, 21]", "bandwidth": 200000, "traffic_string": "0,200000,625,10,2,160,320,480"}, {"origin_node": 129, "destination": 21, "origin_node_antenna": 9, "path": "[129, 9, 13, 14, 16, 2, 11, 10, 19, 18, 21]", "bandwidth": 200000, "traffic_string": "0,200000,625,10,2,160,320,480"}, {"origin_node": 133, "destination": 21, "origin_node_antenna": 9, "path": "[133, 9, 15, 16, 2, 11, 10, 19, 18, 21]", "bandwidth": 200000, "traffic_string": "0,200000,625,10,2,160,320,480"}, {"origin_node": 136, "destination": 21, "origin_node_antenna": 9, "path": "[136, 9, 15, 16, 2, 11, 10, 19, 18, 21]", "bandwidth": 200000, "traffic_string": "0,200000,625,10,2,160,320,480"}], "delta": 0.094, "type": "mMTC", "number": 0}, {"flows": [{"origin_node": 33, "destination": 21, "origin_node_antenna": 5, "path": "[33, 5, 8, 6, 14, 0, 1, 3, 2, 16, 17, 18, 21]", "bandwidth": 200000, "traffic_string": "0,200000,625,10,2,160,320,480"}, {"origin_node": 51, "destination": 21, "origin_node_antenna": 5, "path": "[51, 5, 8, 6, 14, 0, 1, 3, 2, 16, 17, 18, 21]", "bandwidth": 200000, "traffic_string": "0,200000,625,10,2,160,320,480"}, {"origin_node": 59, "destination": 21, "origin_node_antenna": 5, "path": "[59, 5, 8, 6, 14, 0, 1, 3, 2, 16, 17, 18, 21]", "bandwidth": 200000, "traffic_string": "0,200000,625,10,2,160,320,480"}, {"origin_node": 61, "destination": 21, "origin_node_antenna": 5, "path": "[61, 5, 8, 6, 14, 0, 1, 3, 2, 16, 17, 18, 21]", "bandwidth": 200000, "traffic_string": "0,200000,625,10,2,160,320,480"}, {"origin_node": 63, "destination": 21, "origin_node_antenna": 5, "path": "[63, 5, 8, 6, 14, 0, 1, 3, 2, 16, 17, 18, 21]", "bandwidth": 200000, "traffic_string": "0,200000,625,10,2,160,320,480"}, {"origin_node": 65, "destination": 21, "origin_node_antenna": 5, "path": "[65, 5, 8, 6, 14, 0, 1, 3, 2, 16, 17, 18, 21]", "bandwidth": 200000, "traffic_string": "0,200000,625,10,2,160,320,480"}, {"origin_node": 66, "destination": 21, "origin_node_antenna": 5, "path": "[66, 5, 8, 6, 14, 0, 1, 3, 2, 16, 17, 18, 21]", "bandwidth": 200000, "traffic_string": "0,200000,625,10,2,160,320,480"}, {"origin_node": 68, "destination": 21, "origin_node_antenna": 5, "path": "[68, 5, 6, 8, 9, 7, 4, 1, 0, 3, 2, 16, 17, 18, 21]", "bandwidth": 200000, "traffic_string": "0,200000,625,10,2,160,320,480"}, {"origin_node": 69, "destination": 21, "origin_node_antenna": 12, "path": "[69, 12, 9, 13, 14, 16, 2, 11, 10, 19, 18, 21]", "bandwidth": 200000, "traffic_string": "0,200000,625,10,2,160,320,480"}, {"origin_node": 90, "destination": 21, "origin_node_antenna": 12, "path": "[90, 12, 9, 13, 14, 16, 2, 11, 10, 19, 18, 21]", "bandwidth": 200000, "traffic_string": "0,200000,625,10,2,160,320,480"}, {"origin_node": 91, "destination": 21, "origin_node_antenna": 12, "path": "[91, 12, 9, 13, 14, 16, 2, 11, 10, 19, 18, 21]", "bandwidth": 200000, "traffic_string": "0,200000,625,10,2,160,320,480"}, {"origin_node": 101, "destination": 21, "origin_node_antenna": 12, "path": "[101, 12, 9, 13, 14, 16, 2, 11, 10, 19, 18, 21]", "bandwidth": 200000, "traffic_string": "0,200000,625,10,2,160,320,480"}, {"origin_node": 104, "destination": 21, "origin_node_antenna": 12, "path": "[104, 12, 9, 13, 14, 16, 2, 11, 10, 19, 18, 21]", "bandwidth": 200000, "traffic_string": "0,200000,625,10,2,160,320,480"}, {"origin_node": 106, "destination": 21, "origin_node_antenna": 12, "path": "[106, 12, 13, 9, 14, 16, 2, 11, 10, 19, 18, 21]", "bandwidth": 200000, "traffic_string": "0,200000,625,10,2,160,320,480"}, {"origin_node": 107, "destination": 21, "origin_node_antenna": 12, "path": "[107, 12, 13, 9, 14, 16, 2, 11, 10, 19, 18, 21]", "bandwidth": 200000, "traffic_string": "0,200000,625,10,2,160,320,480"}, {"origin_node": 108, "destination": 21, "origin_node_antenna": 12, "path": "[108, 12, 13, 9, 14, 16, 2, 11, 10, 19, 18, 21]", "bandwidth": 200000, "traffic_string": "0,200000,625,10,2,160,320,480"}, {"origin_node": 109, "destination": 21, "origin_node_antenna": 12, "path": "[109, 12, 13, 9, 14, 16, 2, 11, 10, 19, 18, 21]", "bandwidth": 200000, "traffic_string": "0,200000,625,10,2,160,320,480"}, {"origin_node": 113, "destination": 21, "origin_node_antenna": 12, "path": "[113, 12, 13, 9, 14, 16, 2, 11, 10, 19, 18, 21]", "bandwidth": 200000, "traffic_string": "0,200000,625,10,2,160,320,480"}, {"origin_node": 114, "destination": 21, "origin_node_antenna": 12, "path": "[114, 12, 13, 9, 14, 16, 2, 11, 10, 19, 18, 21]", "bandwidth": 200000, "traffic_string": "0,200000,625,10,2,160,320,480"}, {"origin_node": 118, "destination": 21, "origin_node_antenna": 9, "path": "[118, 9, 13, 14, 16, 2, 11, 10, 19, 18, 21]", "bandwidth": 200000, "traffic_string": "0,200000,625,10,2,160,320,480"}, {"origin_node": 119, "destination": 21, "origin_node_antenna": 9, "path": "[119, 9, 13, 14, 16, 2, 11, 10, 19, 18, 21]", "bandwidth": 200000, "traffic_string": "0,200000,625,10,2,160,320,480"}, {"origin_node": 120, "destination": 21, "origin_node_antenna": 9, "path": "[120, 9, 13, 14, 16, 2, 11, 10, 19, 18, 21]", "bandwidth": 200000, "traffic_string": "0,200000,625,10,2,160,320,480"}, {"origin_node": 121, "destination": 21, "origin_node_antenna": 9, "path": "[121, 9, 13, 14, 16, 2, 11, 10, 19, 18, 21]", "bandwidth": 200000, "traffic_string": "0,200000,625,10,2,160,320,480"}, {"origin_node": 122, "destination": 21, "origin_node_antenna": 9, "path": "[122, 9, 13, 14, 16, 2, 11, 10, 19, 18, 21]", "bandwidth": 200000, "traffic_string": "0,200000,625,10,2,160,320,480"}, {"origin_node": 124, "destination": 21, "origin_node_antenna": 9, "path": "[124, 9, 13, 14, 16, 2, 11, 10, 19, 18, 21]", "bandwidth": 200000, "traffic_string": "0,200000,625,10,2,160,320,480"}, {"origin_node": 130, "destination": 21, "origin_node_antenna": 9, "path": "[130, 9, 15, 16, 2, 11, 10, 19, 18, 21]", "bandwidth": 200000, "traffic_string": "0,200000,625,10,2,160,320,480"}, {"origin_node": 131, "destination": 21, "origin_node_antenna": 9, "path": "[131, 9, 15, 16, 2, 11, 10, 19, 18, 21]", "bandwidth": 200000, "traffic_string": "0,200000,625,10,2,160,320,480"}, {"origin_node": 132, "destination": 21, "origin_node_antenna": 9, "path": "[132, 9, 15, 16, 2, 11, 10, 19, 18, 21]", "bandwidth": 200000, "traffic_string": "0,200000,625,10,2,160,320,480"}, {"origin_node": 134, "destination": 21, "origin_node_antenna": 9, "path": "[134, 9, 15, 16, 2, 11, 10, 19, 18, 21]", "bandwidth": 200000, "traffic_string": "0,200000,625,10,2,160,320,480"}, {"origin_node": 135, "destination": 21, "origin_node_antenna": 9, "path": "[135, 9, 15, 16, 2, 11, 10, 19, 18, 21]", "bandwidth": 200000, "traffic_string": "0,200000,625,10,2,160,320,480"}], "delta": 0.849, "type": "mMTC", "number": 1}, {"flows": [{"origin_node": 28, "destination": 20, "origin_node_antenna": 5, "path": "[28, 5, 8, 6, 14, 0, 1, 3, 2, 16, 15, 20]", "bandwidth": 3500000, "traffic_string": "0,3500000,3770,10,2,928,256,1600"}, {"origin_node": 32, "destination": 20, "origin_node_antenna": 5, "path": "[32, 5, 8, 6, 14, 0, 1, 3, 2, 16, 15, 20]", "bandwidth": 3500000, "traffic_string": "0,3500000,3770,10,2,928,256,1600"}, {"origin_node": 34, "destination": 20, "origin_node_antenna": 5, "path": "[34, 5, 8, 6, 14, 0, 1, 3, 2, 16, 15, 20]", "bandwidth": 3500000, "traffic_string": "0,3500000,3770,10,2,928,256,1600"}, {"origin_node": 40, "destination": 20, "origin_node_antenna": 5, "path": "[40, 5, 6, 8, 9, 7, 4, 1, 0, 3, 2, 16, 15, 20]", "bandwidth": 3500000, "traffic_string": "0,3500000,3770,10,2,928,256,1600"}, {"origin_node": 72, "destination": 20, "origin_node_antenna": 12, "path": "[72, 12, 9, 15, 20]", "bandwidth": 3500000, "traffic_string": "0,3500000,3770,10,2,928,256,1600"}, {"origin_node": 73, "destination": 20, "origin_node_antenna": 12, "path": "[73, 12, 9, 15, 20]", "bandwidth": 3500000, "traffic_string": "0,3500000,3770,10,2,928,256,1600"}, {"origin_node": 88, "destination": 20, "origin_node_antenna": 12, "path": "[88, 12, 13, 9, 15, 20]", "bandwidth": 3500000, "traffic_string": "0,3500000,3770,10,2,928,256,1600"}], "delta": 0.888, "type": "URLLC", "number": 0}, {"flows": [{"origin_node": 27, "destination": 20, "origin_node_antenna": 5, "path": "[27, 5, 8, 6, 14, 0, 1, 3, 2, 16, 15, 20]", "bandwidth": 3500000, "traffic_string": "0,3500000,3770,10,2,928,256,1600"}, {"origin_node": 31, "destination": 20, "origin_node_antenna": 5, "path": "[31, 5, 8, 6, 14, 0, 1, 3, 2, 16, 15, 20]", "bandwidth": 3500000, "traffic_string": "0,3500000,3770,10,2,928,256,1600"}, {"origin_node": 45, "destination": 20, "origin_node_antenna": 5, "path": "[45, 5, 6, 8, 9, 7, 4, 1, 0, 3, 2, 16, 15, 20]", "bandwidth": 3500000, "traffic_string": "0,3500000,3770,10,2,928,256,1600"}, {"origin_node": 47, "destination": 20, "origin_node_antenna": 5, "path": "[47, 5, 6, 8, 9, 12, 13, 14, 16, 15, 20]", "bandwidth": 3500000, "traffic_string": "0,3500000,3770,10,2,928,256,1600"}, {"origin_node": 54, "destination": 20, "origin_node_antenna": 5, "path": "[54, 5, 6, 8, 9, 15, 20]", "bandwidth": 3500000, "traffic_string": "0,3500000,3770,10,2,928,256,1600"}, {"origin_node": 75, "destination": 20, "origin_node_antenna": 12, "path": "[75, 12, 9, 15, 20]", "bandwidth": 3500000, "traffic_string": "0,3500000,3770,10,2,928,256,1600"}, {"origin_node": 76, "destination": 20, "origin_node_antenna": 12, "path": "[76, 12, 9, 15, 20]", "bandwidth": 3500000, "traffic_string": "0,3500000,3770,10,2,928,256,1600"}, {"origin_node": 77, "destination": 20, "origin_node_antenna": 12, "path": "[77, 12, 9, 15, 20]", "bandwidth": 3500000, "traffic_string": "0,3500000,3770,10,2,928,256,1600"}, {"origin_node": 115, "destination": 20, "origin_node_antenna": 9, "path": "[115, 9, 15, 20]", "bandwidth": 3500000, "traffic_string": "0,3500000,3770,10,2,928,256,1600"}, {"origin_node": 117, "destination": 20, "origin_node_antenna": 9, "path": "[117, 9, 15, 20]", "bandwidth": 3500000, "traffic_string": "0,3500000,3770,10,2,928,256,1600"}], "delta": 0.294, "type": "URLLC", "number": 1}, {"flows": [{"origin_node": 26, "destination": 20, "origin_node_antenna": 5, "path": "[26, 5, 8, 6, 14, 0, 1, 3, 2, 16, 15, 20]", "bandwidth": 3500000, "traffic_string": "0,3500000,3770,10,2,928,256,1600"}, {"origin_node": 30, "destination": 20, "origin_node_antenna": 5, "path": "[30, 5, 8, 6, 14, 0, 1, 3, 2, 16, 15, 20]", "bandwidth": 3500000, "traffic_string": "0,3500000,3770,10,2,928,256,1600"}, {"origin_node": 39, "destination": 20, "origin_node_antenna": 5, "path": "[39, 5, 6, 8, 9, 7, 4, 1, 0, 3, 2, 16, 15, 20]", "bandwidth": 3500000, "traffic_string": "0,3500000,3770,10,2,928,256,1600"}, {"origin_node": 42, "destination": 20, "origin_node_antenna": 5, "path": "[42, 5, 6, 8, 9, 7, 4, 1, 0, 3, 2, 16, 15, 20]", "bandwidth": 3500000, "traffic_string": "0,3500000,3770,10,2,928,256,1600"}, {"origin_node": 46, "destination": 20, "origin_node_antenna": 5, "path": "[46, 5, 6, 8, 9, 7, 4, 1, 0, 3, 2, 16, 15, 20]", "bandwidth": 3500000, "traffic_string": "0,3500000,3770,10,2,928,256,1600"}, {"origin_node": 52, "destination": 20, "origin_node_antenna": 5, "path": "[52, 5, 6, 8, 9, 12, 13, 14, 16, 15, 20]", "bandwidth": 3500000, "traffic_string": "0,3500000,3770,10,2,928,256,1600"}, {"origin_node": 71, "destination": 20, "origin_node_antenna": 12, "path": "[71, 12, 9, 15, 20]", "bandwidth": 3500000, "traffic_string": "0,3500000,3770,10,2,928,256,1600"}, {"origin_node": 79, "destination": 20, "origin_node_antenna": 12, "path": "[79, 12, 9, 15, 20]", "bandwidth": 3500000, "traffic_string": "0,3500000,3770,10,2,928,256,1600"}, {"origin_node": 80, "destination": 20, "origin_node_antenna": 12, "path": "[80, 12, 9, 15, 20]", "bandwidth": 3500000, "traffic_string": "0,3500000,3770,10,2,928,256,1600"}], "delta": 0.733, "type": "URLLC", "number": 2}, {"flows": [{"origin_node": 29, "destination": 20, "origin_node_antenna": 5, "path": "[29, 5, 8, 6, 14, 0, 1, 3, 2, 16, 15, 20]", "bandwidth": 3500000, "traffic_string": "0,3500000,3770,10,2,928,256,1600"}, {"origin_node": 37, "destination": 20, "origin_node_antenna": 5, "path": "[37, 5, 8, 6, 14, 0, 1, 3, 2, 16, 15, 20]", "bandwidth": 3500000, "traffic_string": "0,3500000,3770,10,2,928,256,1600"}, {"origin_node": 38, "destination": 20, "origin_node_antenna": 5, "path": "[38, 5, 8, 6, 14, 0, 1, 3, 2, 16, 15, 20]", "bandwidth": 3500000, "traffic_string": "0,3500000,3770,10,2,928,256,1600"}, {"origin_node": 41, "destination": 20, "origin_node_antenna": 5, "path": "[41, 5, 6, 8, 9, 7, 4, 1, 0, 3, 2, 16, 15, 20]", "bandwidth": 3500000, "traffic_string": "0,3500000,3770,10,2,928,256,1600"}, {"origin_node": 48, "destination": 20, "origin_node_antenna": 5, "path": "[48, 5, 6, 8, 9, 12, 13, 14, 16, 15, 20]", "bandwidth": 3500000, "traffic_string": "0,3500000,3770,10,2,928,256,1600"}, {"origin_node": 74, "destination": 20, "origin_node_antenna": 12, "path": "[74, 12, 9, 15, 20]", "bandwidth": 3500000, "traffic_string": "0,3500000,3770,10,2,928,256,1600"}, {"origin_node": 78, "destination": 20, "origin_node_antenna": 12, "path": "[78, 12, 9, 15, 20]", "bandwidth": 3500000, "traffic_string": "0,3500000,3770,10,2,928,256,1600"}, {"origin_node": 89, "destination": 20, "origin_node_antenna": 12, "path": "[89, 12, 13, 9, 15, 20]", "bandwidth": 3500000, "traffic_string": "0,3500000,3770,10,2,928,256,1600"}, {"origin_node": 116, "destination": 20, "origin_node_antenna": 9, "path": "[116, 9, 15, 20]", "bandwidth": 3500000, "traffic_string": "0,3500000,3770,10,2,928,256,1600"}], "delta": 0.607, "type": "URLLC", "number": 3}, {"flows": [{"origin_node": 53, "destination": 20, "origin_node_antenna": 5, "path": "[53, 5, 6, 8, 9, 12, 13, 14, 16, 15, 20]", "bandwidth": 3500000, "traffic_string": "0,3500000,3770,10,2,928,256,1600"}, {"origin_node": 82, "destination": 20, "origin_node_antenna": 12, "path": "[82, 12, 13, 9, 15, 20]", "bandwidth": 3500000, "traffic_string": "0,3500000,3770,10,2,928,256,1600"}, {"origin_node": 83, "destination": 20, "origin_node_antenna": 12, "path": "[83, 12, 13, 9, 15, 20]", "bandwidth": 3500000, "traffic_string": "0,3500000,3770,10,2,928,256,1600"}, {"origin_node": 84, "destination": 20, "origin_node_antenna": 12, "path": "[84, 12, 13, 9, 15, 20]", "bandwidth": 3500000, "traffic_string": "0,3500000,3770,10,2,928,256,1600"}, {"origin_node": 86, "destination": 20, "origin_node_antenna": 12, "path": "[86, 12, 13, 9, 15, 20]", "bandwidth": 3500000, "traffic_string": "0,3500000,3770,10,2,928,256,1600"}, {"origin_node": 92, "destination": 20, "origin_node_antenna": 12, "path": "[92, 12, 13, 9, 15, 20]", "bandwidth": 3500000, "traffic_string": "0,3500000,3770,10,2,928,256,1600"}], "delta": 0.271, "type": "URLLC", "number": 4}]