[{"flows": [{"origin_node": 36, "destination": 32, "origin_node_antenna": 15, "path": "[36, 15, 22, 3, 0, 21, 20, 29, 27, 10, 32]", "bandwidth": 18000000, "traffic_string": "0,18000000,1500,10,2,6000,12000,18000"}], "delta": 0.847, "type": "eMBB", "number": 0}, {"flows": [{"origin_node": 33, "destination": 32, "origin_node_antenna": 15, "path": "[33, 15, 22, 3, 0, 21, 20, 29, 27, 10, 32]", "bandwidth": 18000000, "traffic_string": "0,18000000,1500,10,2,6000,12000,18000"}, {"origin_node": 34, "destination": 32, "origin_node_antenna": 24, "path": "[34, 24, 25, 22, 3, 0, 21, 20, 29, 27, 10, 32]", "bandwidth": 18000000, "traffic_string": "0,18000000,1500,10,2,6000,12000,18000"}], "delta": 0.944, "type": "eMBB", "number": 1}, {"flows": [{"origin_node": 39, "destination": 32, "origin_node_antenna": 15, "path": "[39, 15, 22, 3, 0, 21, 20, 29, 27, 10, 32]", "bandwidth": 18000000, "traffic_string": "0,18000000,1500,10,2,6000,12000,18000"}], "delta": 0.921, "type": "eMBB", "number": 2}, {"flows": [{"origin_node": 40, "destination": 32, "origin_node_antenna": 15, "path": "[40, 15, 22, 27, 10, 32]", "bandwidth": 18000000, "traffic_string": "0,18000000,1500,10,2,6000,12000,18000"}], "delta": 0.162, "type": "eMBB", "number": 3}, {"flows": [{"origin_node": 48, "destination": 31, "origin_node_antenna": 15, "path": "[48, 15, 22, 3, 0, 21, 20, 29, 27, 28, 31]", "bandwidth": 200000, "traffic_string": "0,200000,625,10,2,160,320,480"}], "delta": 0.049, "type": "mMTC", "number": 0}, {"flows": [{"origin_node": 46, "destination": 31, "origin_node_antenna": 15, "path": "[46, 15, 22, 3, 0, 21, 20, 29, 27, 28, 31]", "bandwidth": 200000, "traffic_string": "0,200000,625,10,2,160,320,480"}, {"origin_node": 80, "destination": 31, "origin_node_antenna": 24, "path": "[80, 24, 25, 22, 27, 28, 31]", "bandwidth": 200000, "traffic_string": "0,200000,625,10,2,160,320,480"}], "delta": 0.342, "type": "mMTC", "number": 1}, {"flows": [{"origin_node": 52, "destination": 31, "origin_node_antenna": 15, "path": "[52, 15, 22, 27, 28, 31]", "bandwidth": 200000, "traffic_string": "0,200000,625,10,2,160,320,480"}], "delta": 0.5, "type": "mMTC", "number": 2}, {"flows": [{"origin_node": 43, "destination": 31, "origin_node_antenna": 15, "path": "[43, 15, 22, 3, 0, 21, 20, 29, 27, 28, 31]", "bandwidth": 200000, "traffic_string": "0,200000,625,10,2,160,320,480"}], "delta": 0.89, "type": "mMTC", "number": 3}, {"flows": [{"origin_node": 51, "destination": 31, "origin_node_antenna": 15, "path": "[51, 15, 22, 3, 0, 21, 20, 29, 27, 28, 31]", "bandwidth": 200000, "traffic_string": "0,200000,625,10,2,160,320,480"}], "delta": 0.132, "type": "mMTC", "number": 4}, {"flows": [{"origin_node": 50, "destination": 31, "origin_node_antenna": 15, "path": "[50, 15, 22, 27, 28, 31]", "bandwidth": 200000, "traffic_string": "0,200000,625,10,2,160,320,480"}], "delta": 0.257, "type": "mMTC", "number": 5}, {"flows": [{"origin_node": 49, "destination": 31, "origin_node_antenna": 15, "path": "[49, 15, 22, 3, 0, 21, 20, 29, 27, 28, 31]", "bandwidth": 200000, "traffic_string": "0,200000,625,10,2,160,320,480"}, {"origin_node": 58, "destination": 31, "origin_node_antenna": 24, "path": "[58, 24, 25, 22, 27, 28, 31]", "bandwidth": 200000, "traffic_string": "0,200000,625,10,2,160,320,480"}], "delta": 0.164, "type": "mMTC", "number": 6}, {"flows": [{"origin_node": 73, "destination": 31, "origin_node_antenna": 24, "path": "[73, 24, 25, 22, 27, 28, 31]", "bandwidth": 200000, "traffic_string": "0,200000,625,10,2,160,320,480"}, {"origin_node": 78, "destination": 31, "origin_node_antenna": 24, "path": "[78, 24, 25, 22, 27, 28, 31]", "bandwidth": 200000, "traffic_string": "0,200000,625,10,2,160,320,480"}], "delta": 0.364, "type": "mMTC", "number": 7}, {"flows": [{"origin_node": 44, "destination": 31, "origin_node_antenna": 15, "path": "[44, 15, 22, 3, 0, 21, 20, 29, 27, 28, 31]", "bandwidth": 200000, "traffic_string": "0,200000,625,10,2,160,320,480"}, {"origin_node": 67, "destination": 31, "origin_node_antenna": 24, "path": "[67, 24, 25, 22, 27, 28, 31]", "bandwidth": 200000, "traffic_string": "0,200000,625,10,2,160,320,480"}], "delta": 0.628, "type": "mMTC", "number": 8}, {"flows": [{"origin_node": 47, "destination": 31, "origin_node_antenna": 15, "path": "[47, 15, 22, 3, 0, 21, 20, 29, 27, 28, 31]", "bandwidth": 200000, "traffic_string": "0,200000,625,10,2,160,320,480"}, {"origin_node": 81, "destination": 31, "origin_node_antenna": 24, "path": "[81, 24, 25, 22, 27, 28, 31]", "bandwidth": 200000, "traffic_string": "0,200000,625,10,2,160,320,480"}], "delta": 0.601, "type": "mMTC", "number": 9}, {"flows": [{"origin_node": 56, "destination": 30, "origin_node_antenna": 24, "path": "[56, 24, 25, 22, 27, 23, 30]", "bandwidth": 3500000, "traffic_string": "0,3500000,3770,10,2,928,256,1600"}, {"origin_node": 64, "destination": 30, "origin_node_antenna": 24, "path": "[64, 24, 25, 22, 27, 23, 30]", "bandwidth": 3500000, "traffic_string": "0,3500000,3770,10,2,928,256,1600"}, {"origin_node": 70, "destination": 30, "origin_node_antenna": 24, "path": "[70, 24, 25, 22, 27, 23, 30]", "bandwidth": 3500000, "traffic_string": "0,3500000,3770,10,2,928,256,1600"}], "delta": 0.463, "type": "URLLC", "number": 0}, {"flows": [{"origin_node": 45, "destination": 30, "origin_node_antenna": 15, "path": "[45, 15, 22, 27, 23, 30]", "bandwidth": 3500000, "traffic_string": "0,3500000,3770,10,2,928,256,1600"}, {"origin_node": 66, "destination": 30, "origin_node_antenna": 24, "path": "[66, 24, 25, 22, 27, 23, 30]", "bandwidth": 3500000, "traffic_string": "0,3500000,3770,10,2,928,256,1600"}], "delta": 0.71, "type": "URLLC", "number": 1}, {"flows": [{"origin_node": 63, "destination": 30, "origin_node_antenna": 24, "path": "[63, 24, 25, 22, 27, 23, 30]", "bandwidth": 3500000, "traffic_string": "0,3500000,3770,10,2,928,256,1600"}, {"origin_node": 65, "destination": 30, "origin_node_antenna": 24, "path": "[65, 24, 25, 22, 27, 23, 30]", "bandwidth": 3500000, "traffic_string": "0,3500000,3770,10,2,928,256,1600"}, {"origin_node": 69, "destination": 30, "origin_node_antenna": 24, "path": "[69, 24, 25, 22, 27, 23, 30]", "bandwidth": 3500000, "traffic_string": "0,3500000,3770,10,2,928,256,1600"}, {"origin_node": 72, "destination": 30, "origin_node_antenna": 24, "path": "[72, 24, 25, 22, 27, 23, 30]", "bandwidth": 3500000, "traffic_string": "0,3500000,3770,10,2,928,256,1600"}], "delta": 0.6, "type": "URLLC", "number": 2}, {"flows": [{"origin_node": 35, "destination": 30, "origin_node_antenna": 15, "path": "[35, 15, 22, 3, 0, 21, 20, 29, 27, 23, 30]", "bandwidth": 3500000, "traffic_string": "0,3500000,3770,10,2,928,256,1600"}, {"origin_node": 55, "destination": 30, "origin_node_antenna": 24, "path": "[55, 24, 25, 22, 27, 23, 30]", "bandwidth": 3500000, "traffic_string": "0,3500000,3770,10,2,928,256,1600"}], "delta": 0.875, "type": "URLLC", "number": 3}, {"flows": [{"origin_node": 68, "destination": 30, "origin_node_antenna": 24, "path": "[68, 24, 25, 22, 27, 23, 30]", "bandwidth": 3500000, "traffic_string": "0,3500000,3770,10,2,928,256,1600"}, {"origin_node": 71, "destination": 30, "origin_node_antenna": 24, "path": "[71, 24, 25, 22, 27, 23, 30]", "bandwidth": 3500000, "traffic_string": "0,3500000,3770,10,2,928,256,1600"}], "delta": 0.613, "type": "URLLC", "number": 4}, {"flows": [{"origin_node": 37, "destination": 30, "origin_node_antenna": 15, "path": "[37, 15, 22, 3, 0, 21, 20, 29, 27, 23, 30]", "bandwidth": 3500000, "traffic_string": "0,3500000,3770,10,2,928,256,1600"}, {"origin_node": 38, "destination": 30, "origin_node_antenna": 15, "path": "[38, 15, 22, 3, 0, 21, 20, 29, 27, 23, 30]", "bandwidth": 3500000, "traffic_string": "0,3500000,3770,10,2,928,256,1600"}, {"origin_node": 42, "destination": 30, "origin_node_antenna": 15, "path": "[42, 15, 22, 3, 0, 21, 20, 29, 27, 23, 30]", "bandwidth": 3500000, "traffic_string": "0,3500000,3770,10,2,928,256,1600"}], "delta": 0.603, "type": "URLLC", "number": 5}, {"flows": [{"origin_node": 61, "destination": 30, "origin_node_antenna": 24, "path": "[61, 24, 25, 22, 27, 23, 30]", "bandwidth": 3500000, "traffic_string": "0,3500000,3770,10,2,928,256,1600"}, {"origin_node": 76, "destination": 30, "origin_node_antenna": 24, "path": "[76, 24, 25, 22, 27, 23, 30]", "bandwidth": 3500000, "traffic_string": "0,3500000,3770,10,2,928,256,1600"}], "delta": 0.635, "type": "URLLC", "number": 6}, {"flows": [{"origin_node": 60, "destination": 30, "origin_node_antenna": 24, "path": "[60, 24, 25, 22, 27, 23, 30]", "bandwidth": 3500000, "traffic_string": "0,3500000,3770,10,2,928,256,1600"}, {"origin_node": 75, "destination": 30, "origin_node_antenna": 24, "path": "[75, 24, 25, 22, 27, 23, 30]", "bandwidth": 3500000, "traffic_string": "0,3500000,3770,10,2,928,256,1600"}], "delta": 0.041, "type": "URLLC", "number": 7}, {"flows": [{"origin_node": 41, "destination": 30, "origin_node_antenna": 15, "path": "[41, 15, 22, 3, 0, 21, 20, 29, 27, 23, 30]", "bandwidth": 3500000, "traffic_string": "0,3500000,3770,10,2,928,256,1600"}, {"origin_node": 59, "destination": 30, "origin_node_antenna": 24, "path": "[59, 24, 25, 22, 27, 23, 30]", "bandwidth": 3500000, "traffic_string": "0,3500000,3770,10,2,928,256,1600"}, {"origin_node": 62, "destination": 30, "origin_node_antenna": 24, "path": "[62, 24, 25, 22, 27, 23, 30]", "bandwidth": 3500000, "traffic_string": "0,3500000,3770,10,2,928,256,1600"}, {"origin_node": 74, "destination": 30, "origin_node_antenna": 24, "path": "[74, 24, 25, 22, 27, 23, 30]", "bandwidth": 3500000, "traffic_string": "0,3500000,3770,10,2,928,256,1600"}, {"origin_node": 77, "destination": 30, "origin_node_antenna": 24, "path": "[77, 24, 25, 22, 27, 23, 30]", "bandwidth": 3500000, "traffic_string": "0,3500000,3770,10,2,928,256,1600"}, {"origin_node": 79, "destination": 30, "origin_node_antenna": 24, "path": "[79, 24, 25, 22, 27, 23, 30]", "bandwidth": 3500000, "traffic_string": "0,3500000,3770,10,2,928,256,1600"}], "delta": 0.005, "type": "URLLC", "number": 8}, {"flows": [{"origin_node": 57, "destination": 30, "origin_node_antenna": 24, "path": "[57, 24, 25, 22, 27, 23, 30]", "bandwidth": 3500000, "traffic_string": "0,3500000,3770,10,2,928,256,1600"}], "delta": 0.213, "type": "URLLC", "number": 9}, {"flows": [{"origin_node": 53, "destination": 30, "origin_node_antenna": 24, "path": "[53, 24, 25, 22, 27, 23, 30]", "bandwidth": 3500000, "traffic_string": "0,3500000,3770,10,2,928,256,1600"}, {"origin_node": 54, "destination": 30, "origin_node_antenna": 24, "path": "[54, 24, 25, 22, 27, 23, 30]", "bandwidth": 3500000, "traffic_string": "0,3500000,3770,10,2,928,256,1600"}], "delta": 0.6, "type": "URLLC", "number": 10}]